readability/__init__.py
readability/readability.py
readability/data/dale_chall_porterstem.txt
readability/data/spache_easy_porterstem.txt
readability/exceptions/__init__.py
readability/scorers/__init__.py
readability/scorers/ari.py
readability/scorers/coleman_liau.py
readability/scorers/dale_chall.py
readability/scorers/flesch.py
readability/scorers/flesch_kincaid.py
readability/scorers/gunning_fog.py
readability/scorers/linsear_write.py
readability/scorers/smog.py
readability/scorers/spache.py
readability/text/__init__.py
readability/text/analyzer.py
readability/text/syllables.py
test/__init__.py
test/test_readability.py
py_readability_metrics-1.4.5.dist-info/LICENSE
py_readability_metrics-1.4.5.dist-info/METADATA
py_readability_metrics-1.4.5.dist-info/WHEEL
py_readability_metrics-1.4.5.dist-info/top_level.txt
py_readability_metrics-1.4.5.dist-info/RECORD
