Metadata-Version: 2.1
Name: py-readability-metrics
Version: 1.4.5
Summary: Score text "Readability" with popular formulas and metrics including Flesch-Kincaid, Gunning Fog, ARI, Dale Chall, SMOG, Spache and more
Home-page: https://github.com/cdimascio/py-readability-metrics
Author: Carmine DiMAscio
Author-email: cdimascio@gmail.com
License: MIT
Keywords: readability metrics text difficulty grade level
Platform: UNKNOWN
Classifier: Programming Language :: Python :: 3
Classifier: License :: OSI Approved :: MIT License
Classifier: Operating System :: OS Independent
